evolve/__init__.py
evolve/aider_async.py
evolve/config.py
evolve/coordinator.py
evolve/database.py
evolve/dspy_async.py
evolve/errors.py
evolve/executor_async.py
evolve/history.py
evolve/prompting/__init__.py
evolve/prompting/models.py
evolve/strategies/__init__.py
evolve/strategies/base.py
evolve/strategies/basic.py
evolve/strategies/islands.py
evolve/strategies/map_elites.py
evolv-0.1.0.dist-info/METADATA
evolv-0.1.0.dist-info/WHEEL
evolv-0.1.0.dist-info/entry_points.txt
evolv-0.1.0.dist-info/licenses/LICENSE
evolv-0.1.0.dist-info/RECORD
