Metadata-Version: 2.4
Name: evolv
Version: 0.1.0
Summary: A Python framework for evolving code using AI.
Project-URL: Homepage, https://github.com/johan-gras/evolve
Project-URL: Repository, https://github.com/johan-gras/evolve
Author-email: Johan Gras <johan.gras-sub@outlook.com>
License: MIT
License-File: LICENSE
Keywords: ai,autonomous agents,code generation,evolutionary algorithms,python
Classifier: Intended Audience :: Developers
Classifier: Intended Audience :: Science/Research
Classifier: License :: OSI Approved :: MIT License
Classifier: Operating System :: OS Independent
Classifier: Programming Language :: Python :: 3
Classifier: Programming Language :: Python :: 3.9
Classifier: Programming Language :: Python :: 3.10
Classifier: Programming Language :: Python :: 3.11
Classifier: Programming Language :: Python :: 3.12
Classifier: Topic :: Scientific/Engineering :: Artificial Intelligence
Classifier: Topic :: Software Development :: Libraries :: Python Modules
Requires-Python: >=3.9
Requires-Dist: aiofiles>=24.1.0
Requires-Dist: dspy>=2.6.27
Requires-Dist: modal>=1.0.3
Requires-Dist: numpy>=2.0.2
Requires-Dist: pandas>=2.3.0
Requires-Dist: python-dotenv>=1.1.0
Requires-Dist: scikit-learn>=1.6.1
Provides-Extra: dev
Requires-Dist: black>=24.0.0; extra == 'dev'
Requires-Dist: mypy>=1.11.0; extra == 'dev'
Requires-Dist: pre-commit>=3.5.0; extra == 'dev'
Requires-Dist: pytest-asyncio>=1.0.0; extra == 'dev'
Requires-Dist: pytest-cov>=4.1.0; extra == 'dev'
Requires-Dist: pytest>=7.0; extra == 'dev'
Requires-Dist: ruff>=0.8.0; extra == 'dev'
Requires-Dist: types-requests>=2.31.0; extra == 'dev'
